AUTHORS
CHANGELOG
LICENSE
MANIFEST.in
README.rst
requirements.txt
setup.py
django_knockback.egg-info/PKG-INFO
django_knockback.egg-info/SOURCES.txt
django_knockback.egg-info/dependency_links.txt
django_knockback.egg-info/requires.txt
django_knockback.egg-info/top_level.txt
knockback/__init__.py
knockback/models.py
knockback/static/backbone.js
knockback/static/jquery.js
knockback/static/knockback.js
knockback/static/knockout.js
knockback/static/underscore.js
knockback/templates/base.html
knockback/templates/knockback.html