Metadata-Version: 1.0
Name: django-knockback
Version: 0.1.1
Summary: A django app that contains the necessary javascript files to use knockback.js
Home-page: https://github.com/thedrow/django-knockback/
Author: Omer Katz
Author-email: omer.drow@gmail.com
License: BSD
Keywords: django,knockout.js,backbone.js,jquery,knockback.js
Platform: UNKNOWN
